npc_engine/__init__.py
npc_engine/cli.py
npc_engine/version.py
npc_engine/server/__init__.py
npc_engine/server/control_service.py
npc_engine/server/metadata_manager.py
npc_engine/server/server.py
npc_engine/server/utils.py
npc_engine/service_clients/__init__.py
npc_engine/service_clients/control_client.py
npc_engine/service_clients/sequence_classifier_client.py
npc_engine/service_clients/service_client.py
npc_engine/service_clients/similarity_client.py
npc_engine/service_clients/text_generation_client.py
npc_engine/services/__init__.py
npc_engine/services/base_service.py
npc_engine/services/factory_mixin.py
npc_engine/services/persona_dialogue/__init__.py
npc_engine/services/persona_dialogue/persona_dialogue.py
npc_engine/services/persona_dialogue/persona_dialogue_base.py
npc_engine/services/sequence_classifier/__init__.py
npc_engine/services/sequence_classifier/hf_classifier.py
npc_engine/services/sequence_classifier/sequence_classifier_base.py
npc_engine/services/similarity/__init__.py
npc_engine/services/similarity/similarity_base.py
npc_engine/services/similarity/similarity_transformers.py
npc_engine/services/text_generation/__init__.py
npc_engine/services/text_generation/bart.py
npc_engine/services/text_generation/hf_text_generation.py
npc_engine/services/text_generation/text_generation_base.py
npc_engine/services/text_generation/utils.py
npc_engine/services/tts/__init__.py
npc_engine/services/tts/espnet_onnx.py
npc_engine/services/tts/tts_base.py
npc_engine/services/tts/flowtron/__init__.py
npc_engine/services/tts/flowtron/flowtron.py
npc_engine/services/tts/flowtron/text/__init__.py
npc_engine/services/tts/flowtron/text/cleaners.py
npc_engine/services/tts/flowtron/text/datestime.py
npc_engine/services/tts/flowtron/text/numbers.py
npc_engine/services/tts/flowtron/text/symbols.py
npc_engine/services/utils/__init__.py
npc_engine/services/utils/config.py
npc_engine/services/utils/lru_cache.py
npc_engine/services/utils/mock.py
npc_engine-0.1.8.dist-info/LICENSE
npc_engine-0.1.8.dist-info/METADATA
npc_engine-0.1.8.dist-info/WHEEL
npc_engine-0.1.8.dist-info/entry_points.txt
npc_engine-0.1.8.dist-info/top_level.txt
npc_engine-0.1.8.dist-info/RECORD
