Metadata-Version: 2.1
Name: npc-engine
Version: 0.1.8
Summary: Deep learning inference and NLP toolkit for game development.
Home-page: https://github.com/npc-engine/npc-engine
Download-URL: https://github.com/npc-engine/npc_engine/archive/0.1.8.tar.gz
Author: eublefar
Author-email: evil.unicorn1@gmail.com
License: MIT
Keywords: npc,AI,inference,deep-learning
Classifier: Development Status :: 3 - Alpha
Classifier: Topic :: Multimedia :: Sound/Audio :: Speech
Classifier: Intended Audience :: Developers
Classifier: Topic :: Scientific/Engineering :: Human Machine Interfaces
Classifier: Operating System :: Microsoft :: Windows
Classifier: Topic :: Software Development :: Libraries
Classifier: License :: OSI Approved :: MIT License
Classifier: Programming Language :: Python :: 3.8
Requires-Python: >=3.8.0,<3.9.0
License-File: LICENSE
Requires-Dist: click (<8,>=7.0)
Requires-Dist: json-rpc (==1.13.0)
Requires-Dist: tokenizers (==0.11.6)
Requires-Dist: loguru (==0.5.3)
Requires-Dist: PyYAML (==6.0)
Requires-Dist: pyzmq (==22.3.0)
Requires-Dist: Unidecode (==1.1.1)
Requires-Dist: inflect (==4.1.0)
Requires-Dist: scipy (==1.7.2)
Requires-Dist: sounddevice (==0.4.3)
Requires-Dist: Jinja2 (==3.0.2)
Requires-Dist: numpy (~=1.21)
Requires-Dist: setuptools (~=57.0.0)
Requires-Dist: huggingface-hub (==0.1.2)
Requires-Dist: librosa (>=0.8.0)
Requires-Dist: numba (==0.48)
Requires-Dist: platformdirs (>=1.0.0)
Requires-Dist: scikit-learn (==1.0.2)
Requires-Dist: jinja2schema (==0.1.4)
Requires-Dist: appdirs (==1.4.4)
Requires-Dist: aiohttp (>=3.8.1)
Requires-Dist: tornado (>6.1.0)
Provides-Extra: benchmarks
Requires-Dist: py3nvml ; extra == 'benchmarks'
Provides-Extra: cpu
Requires-Dist: onnxruntime (<2.0.0,>=1.8.0) ; extra == 'cpu'
Provides-Extra: deploy
Requires-Dist: pip-licenses (>=3.5.3) ; extra == 'deploy'
Requires-Dist: pyinstaller (==5.0) ; extra == 'deploy'
Provides-Extra: dev
Requires-Dist: pip-check-reqs (<3,>=2.0.1) ; extra == 'dev'
Requires-Dist: black (>=19.10b0) ; extra == 'dev'
Requires-Dist: flake8 (<4,>=3.7.9) ; extra == 'dev'
Requires-Dist: flake8-docstrings (<2,>=1.5.0) ; extra == 'dev'
Requires-Dist: pytest (>=6.0.1) ; extra == 'dev'
Requires-Dist: pytest-cov (<3,>=2.5.1) ; extra == 'dev'
Requires-Dist: pytest-pythonpath (<1,>=0.7.2) ; extra == 'dev'
Requires-Dist: setuptools (>=38.4.0) ; extra == 'dev'
Requires-Dist: tox (<4,>=3.0.0) ; extra == 'dev'
Requires-Dist: twine (==3.2.0) ; extra == 'dev'
Requires-Dist: pydub ; extra == 'dev'
Requires-Dist: sclblonnx (==0.1.9) ; extra == 'dev'
Requires-Dist: pytest-asyncio (>=0.18.3) ; extra == 'dev'
Provides-Extra: dml
Requires-Dist: onnxruntime-directml (<2.0.0,>=1.8.0) ; extra == 'dml'
Provides-Extra: doc
Requires-Dist: mkdocs (>=1.2.3) ; extra == 'doc'
Requires-Dist: mkdocstrings[python] (==0.18.0) ; extra == 'doc'
Requires-Dist: mkdocs-material (>=7.3.6) ; extra == 'doc'
Requires-Dist: mike (>=1.1.2) ; extra == 'doc'
